qbox_factor_client/__init__.py
qbox_factor_client/factor.py
qbox_factor_client/py.typed
qbox_factor_client-0.1.4.dist-info/METADATA
qbox_factor_client-0.1.4.dist-info/WHEEL
qbox_factor_client-0.1.4.dist-info/top_level.txt
qbox_factor_client-0.1.4.dist-info/RECORD
