Metadata-Version: 2.4
Name: qbox-factor-client
Version: 0.1.4
Summary: Python client for the QBox Factor API - query market factor data easily
Author-email: QBox Team <dev@qbox.ai>
License-Expression: MIT
Project-URL: Homepage, https://github.com/qbox-team/qbox-factor-api
Project-URL: Documentation, https://github.com/qbox-team/qbox-factor-api/blob/main/docs/qbox_factor_client_guide.md
Project-URL: Repository, https://github.com/qbox-team/qbox-factor-api
Project-URL: Issues, https://github.com/qbox-team/qbox-factor-api/issues
Keywords: finance,factor,api,client,quantitative,market-data
Classifier: Development Status :: 4 - Beta
Classifier: Intended Audience :: Financial and Insurance Industry
Classifier: Intended Audience :: Developers
Classifier: Programming Language :: Python :: 3
Classifier: Programming Language :: Python :: 3.8
Classifier: Programming Language :: Python :: 3.9
Classifier: Programming Language :: Python :: 3.10
Classifier: Programming Language :: Python :: 3.11
Classifier: Programming Language :: Python :: 3.12
Classifier: Topic :: Office/Business :: Financial
Classifier: Topic :: Software Development :: Libraries :: Python Modules
Requires-Python: >=3.8
Requires-Dist: httpx>=0.24.0
Requires-Dist: pandas>=1.5.0
Provides-Extra: analysis
Requires-Dist: numpy>=1.21.0; extra == "analysis"
Requires-Dist: matplotlib>=3.5.0; extra == "analysis"
Requires-Dist: seaborn>=0.11.0; extra == "analysis"
Provides-Extra: dev
Requires-Dist: pytest>=7.0.0; extra == "dev"
Requires-Dist: black>=23.0.0; extra == "dev"
Requires-Dist: isort>=5.12.0; extra == "dev"
Requires-Dist: mypy>=1.0.0; extra == "dev"
